hicrepcm/__init__.py
hicrepcm/hicrepcm.py
hicrepcm-0.5.0.dist-info/LICENSE
hicrepcm-0.5.0.dist-info/METADATA
hicrepcm-0.5.0.dist-info/WHEEL
hicrepcm-0.5.0.dist-info/entry_points.txt
hicrepcm-0.5.0.dist-info/top_level.txt
hicrepcm-0.5.0.dist-info/RECORD
