Metadata-Version: 2.1
Name: hicrepcm
Version: 0.5.0
Requires-Python: >=3.6
License-File: LICENSE
Requires-Dist: hicrep
Requires-Dist: numpy
Requires-Dist: matplotlib
Requires-Dist: seaborn
Requires-Dist: colorcet
